README.md
setup.py
drescher/__init__.py
drescher/endpoints.py
drescher/models.py
drescher/utils.py
drescher_client.egg-info/PKG-INFO
drescher_client.egg-info/SOURCES.txt
drescher_client.egg-info/dependency_links.txt
drescher_client.egg-info/requires.txt
drescher_client.egg-info/top_level.txt