Metadata-Version: 1.0
Name: drescher-client
Version: 2.0.0
Summary: The public Drescher API client
Home-page: UNKNOWN
Author: UNKNOWN
Author-email: UNKNOWN
License: UNKNOWN
Platform: UNKNOWN
